Metadata-Version: 2.1
Name: odoo-addon-account_move_line_due_date
Version: 17.0.1.0.0
Requires-Python: >=3.10
Requires-Dist: odoo>=17.0a,<17.1dev
Summary: Shows Date Maturity on Journal Entries Lines
Home-page: https://github.com/sygel-technology/sy-account-financial-tools
License: AGPL-3
Author: Sygel
Classifier: Programming Language :: Python
Classifier: Framework :: Odoo
Classifier: Framework :: Odoo :: 17.0
Classifier: License :: OSI Approved :: GNU Affero General Public License v3
